streamlit_discourse/__init__.py
streamlit_discourse/frontend/build/asset-manifest.json
streamlit_discourse/frontend/build/bootstrap.min.css
streamlit_discourse/frontend/build/index.html
streamlit_discourse/frontend/build/precache-manifest.83b0bd8a8ce386e3bf0fe7e27447b4e1.js
streamlit_discourse/frontend/build/service-worker.js
streamlit_discourse/frontend/build/static/js/2.8bf4e17c.chunk.js
streamlit_discourse/frontend/build/static/js/2.8bf4e17c.chunk.js.LICENSE.txt
streamlit_discourse/frontend/build/static/js/2.8bf4e17c.chunk.js.map
streamlit_discourse/frontend/build/static/js/main.3f9c07f9.chunk.js
streamlit_discourse/frontend/build/static/js/main.3f9c07f9.chunk.js.map
streamlit_discourse/frontend/build/static/js/runtime-main.7e8c6cf9.js
streamlit_discourse/frontend/build/static/js/runtime-main.7e8c6cf9.js.map
streamlit_discourse-0.1.3.dist-info/LICENSE
streamlit_discourse-0.1.3.dist-info/METADATA
streamlit_discourse-0.1.3.dist-info/WHEEL
streamlit_discourse-0.1.3.dist-info/top_level.txt
streamlit_discourse-0.1.3.dist-info/RECORD
