Metadata-Version: 2.1
Name: streamlit-discourse
Version: 0.1.3
Summary: A streamlit component to embed Discourse topics in your applications.
Home-page: https://github.com/okld/streamlit-discourse
Author: okld
Author-email: 
License: UNKNOWN
Platform: UNKNOWN
Requires-Python: >=3.6
Requires-Dist: streamlit (>=0.73)
